{
  "audioUrl": "https://utfs.io/f/Gv2JxtlSEriPdGvgfWm4BviyXHhL6DCU7PQJtmObnsxZaquf",
  "images": [
    "https://utfs.io/f/Gv2JxtlSEriPsXbbiVQDIhG9TSgNWDL1Epn48PBvC0J2jZkU",
    "https://utfs.io/f/Gv2JxtlSEriPWGh1WgZ1oWnbPDqRVGSAl8ud4Kap2YE7Fmer",
    "https://utfs.io/f/Gv2JxtlSEriPOVI2s8cRY0BfuPoL3NhqvnkUmA8j4VK756ai",
    "https://utfs.io/f/Gv2JxtlSEriPQxSiIcAMDKVuLdAoEecR2t0y7vb1lXpjZsQY"
  ],
  "words": [
    {
      "word": "welcome",
      "start": 0.16,
      "end": 0.32,
      "confidence": 0.99939096,
      "punctuated_word": "Welcome"
    },
    {
      "word": "to",
      "start": 0.32,
      "end": 0.48,
      "confidence": 0.9998178,
      "punctuated_word": "to"
    },
    {
      "word": "the",
      "start": 0.48,
      "end": 0.71999997,
      "confidence": 0.9998776,
      "punctuated_word": "the"
    },
    {
      "word": "world",
      "start": 0.71999997,
      "end": 0.96,
      "confidence": 0.99527377,
      "punctuated_word": "world"
    },
    {
      "word": "of",
      "start": 0.96,
      "end": 1.1999999,
      "confidence": 0.99956554,
      "punctuated_word": "of"
    },
    {
      "word": "soccer",
      "start": 1.1999999,
      "end": 1.5999999,
      "confidence": 0.99815136,
      "punctuated_word": "soccer"
    },
    {
      "word": "where",
      "start": 1.5999999,
      "end": 1.8399999,
      "confidence": 0.8824031,
      "punctuated_word": "where"
    },
    {
      "word": "one",
      "start": 1.8399999,
      "end": 2.08,
      "confidence": 0.96662027,
      "punctuated_word": "one"
    },
    {
      "word": "of",
      "start": 2.08,
      "end": 2.1599998,
      "confidence": 0.9999007,
      "punctuated_word": "of"
    },
    {
      "word": "the",
      "start": 2.1599998,
      "end": 2.32,
      "confidence": 0.9996538,
      "punctuated_word": "the"
    },
    {
      "word": "greatest",
      "start": 2.32,
      "end": 2.6399999,
      "confidence": 0.99979466,
      "punctuated_word": "greatest"
    },
    {
      "word": "players",
      "start": 2.6399999,
      "end": 3.04,
      "confidence": 0.9989266,
      "punctuated_word": "players"
    },
    {
      "word": "of",
      "start": 3.04,
      "end": 3.1999998,
      "confidence": 0.9998945,
      "punctuated_word": "of"
    },
    {
      "word": "all",
      "start": 3.1999998,
      "end": 3.4399998,
      "confidence": 0.9996001,
      "punctuated_word": "all"
    },
    {
      "word": "time",
      "start": 3.4399998,
      "end": 3.9399998,
      "confidence": 0.94520164,
      "punctuated_word": "time,"
    },
    {
      "word": "cristiano",
      "start": 4.08,
      "end": 4.58,
      "confidence": 0.993696,
      "punctuated_word": "Cristiano"
    },
    {
      "word": "ronaldo",
      "start": 4.72,
      "end": 5.22,
      "confidence": 0.8980274,
      "punctuated_word": "Ronaldo,"
    },
    {
      "word": "has",
      "start": 5.3599997,
      "end": 5.52,
      "confidence": 0.999579,
      "punctuated_word": "has"
    },
    {
      "word": "made",
      "start": 5.52,
      "end": 5.7599998,
      "confidence": 0.99990904,
      "punctuated_word": "made"
    },
    {
      "word": "his",
      "start": 5.7599998,
      "end": 6,
      "confidence": 0.9998355,
      "punctuated_word": "his"
    },
    {
      "word": "mark",
      "start": 6,
      "end": 6.16,
      "confidence": 0.9990397,
      "punctuated_word": "mark"
    },
    {
      "word": "with",
      "start": 6.16,
      "end": 6.48,
      "confidence": 0.9995301,
      "punctuated_word": "with"
    },
    {
      "word": "incredible",
      "start": 6.48,
      "end": 6.98,
      "confidence": 0.99928385,
      "punctuated_word": "incredible"
    },
    {
      "word": "speed",
      "start": 7.12,
      "end": 7.62,
      "confidence": 0.9979451,
      "punctuated_word": "speed,"
    },
    {
      "word": "skill",
      "start": 7.8399997,
      "end": 8.16,
      "confidence": 0.9831364,
      "punctuated_word": "skill,"
    },
    {
      "word": "and",
      "start": 8.16,
      "end": 8.4,
      "confidence": 0.99970835,
      "punctuated_word": "and"
    },
    {
      "word": "determination",
      "start": 8.4,
      "end": 8.9,
      "confidence": 0.9994709,
      "punctuated_word": "determination."
    },
    {
      "word": "born",
      "start": 9.679999,
      "end": 9.92,
      "confidence": 0.9951434,
      "punctuated_word": "Born"
    },
    {
      "word": "in",
      "start": 9.92,
      "end": 10.16,
      "confidence": 0.9986914,
      "punctuated_word": "in"
    },
    {
      "word": "madera",
      "start": 10.16,
      "end": 10.639999,
      "confidence": 0.92339975,
      "punctuated_word": "Madera,"
    },
    {
      "word": "portugal",
      "start": 10.639999,
      "end": 11.139999,
      "confidence": 0.9014566,
      "punctuated_word": "Portugal,"
    },
    {
      "word": "ronaldo",
      "start": 11.2,
      "end": 11.7,
      "confidence": 0.9921491,
      "punctuated_word": "Ronaldo"
    },
    {
      "word": "grew",
      "start": 11.759999,
      "end": 12,
      "confidence": 0.99418724,
      "punctuated_word": "grew"
    },
    {
      "word": "up",
      "start": 12,
      "end": 12.16,
      "confidence": 0.999569,
      "punctuated_word": "up"
    },
    {
      "word": "with",
      "start": 12.16,
      "end": 12.465,
      "confidence": 0.7680994,
      "punctuated_word": "with."
    },
    {
      "word": "a",
      "start": 12.545,
      "end": 12.785,
      "confidence": 0.9980305,
      "punctuated_word": "A"
    },
    {
      "word": "passion",
      "start": 12.785,
      "end": 12.945,
      "confidence": 0.999411,
      "punctuated_word": "passion"
    },
    {
      "word": "for",
      "start": 12.945,
      "end": 13.345,
      "confidence": 0.9993174,
      "punctuated_word": "for"
    },
    {
      "word": "soccer",
      "start": 13.345,
      "end": 13.745,
      "confidence": 0.9993864,
      "punctuated_word": "soccer"
    },
    {
      "word": "and",
      "start": 13.745,
      "end": 13.985001,
      "confidence": 0.8919721,
      "punctuated_word": "and"
    },
    {
      "word": "his",
      "start": 13.985001,
      "end": 14.145,
      "confidence": 0.9991912,
      "punctuated_word": "his"
    },
    {
      "word": "hard",
      "start": 14.145,
      "end": 14.385,
      "confidence": 0.9994838,
      "punctuated_word": "hard"
    },
    {
      "word": "work",
      "start": 14.385,
      "end": 14.545,
      "confidence": 0.9986355,
      "punctuated_word": "work"
    },
    {
      "word": "and",
      "start": 14.545,
      "end": 14.785,
      "confidence": 0.9801307,
      "punctuated_word": "and"
    },
    {
      "word": "dedication",
      "start": 14.785,
      "end": 15.285,
      "confidence": 0.9999238,
      "punctuated_word": "dedication"
    },
    {
      "word": "took",
      "start": 15.345,
      "end": 15.505,
      "confidence": 0.9988323,
      "punctuated_word": "took"
    },
    {
      "word": "him",
      "start": 15.505,
      "end": 15.745,
      "confidence": 0.9995958,
      "punctuated_word": "him"
    },
    {
      "word": "from",
      "start": 15.745,
      "end": 15.985001,
      "confidence": 0.9982962,
      "punctuated_word": "from"
    },
    {
      "word": "playing",
      "start": 15.985001,
      "end": 16.225,
      "confidence": 0.9992071,
      "punctuated_word": "playing"
    },
    {
      "word": "with",
      "start": 16.225,
      "end": 16.465,
      "confidence": 0.9973954,
      "punctuated_word": "with"
    },
    {
      "word": "his",
      "start": 16.465,
      "end": 16.625,
      "confidence": 0.9976453,
      "punctuated_word": "his"
    },
    {
      "word": "friends",
      "start": 16.625,
      "end": 16.945,
      "confidence": 0.99953246,
      "punctuated_word": "friends"
    },
    {
      "word": "in",
      "start": 16.945,
      "end": 17.105,
      "confidence": 0.9891761,
      "punctuated_word": "in"
    },
    {
      "word": "the",
      "start": 17.105,
      "end": 17.185,
      "confidence": 0.99946266,
      "punctuated_word": "the"
    },
    {
      "word": "streets",
      "start": 17.185,
      "end": 17.585,
      "confidence": 0.99872154,
      "punctuated_word": "streets"
    },
    {
      "word": "to",
      "start": 17.585,
      "end": 17.744999,
      "confidence": 0.9969363,
      "punctuated_word": "to"
    },
    {
      "word": "becoming",
      "start": 17.744999,
      "end": 18.225,
      "confidence": 0.98722744,
      "punctuated_word": "becoming"
    },
    {
      "word": "a",
      "start": 18.225,
      "end": 18.465,
      "confidence": 0.9964833,
      "punctuated_word": "a"
    },
    {
      "word": "professional",
      "start": 18.465,
      "end": 18.945,
      "confidence": 0.9996269,
      "punctuated_word": "professional"
    },
    {
      "word": "player",
      "start": 18.945,
      "end": 19.345,
      "confidence": 0.99898857,
      "punctuated_word": "player"
    },
    {
      "word": "at",
      "start": 19.345,
      "end": 19.505001,
      "confidence": 0.99888533,
      "punctuated_word": "at"
    },
    {
      "word": "a",
      "start": 19.505001,
      "end": 19.585,
      "confidence": 0.9972771,
      "punctuated_word": "a"
    },
    {
      "word": "young",
      "start": 19.585,
      "end": 19.825,
      "confidence": 0.9999069,
      "punctuated_word": "young"
    },
    {
      "word": "age",
      "start": 19.825,
      "end": 20.325,
      "confidence": 0.99913055,
      "punctuated_word": "age"
    },
    {
      "word": "with",
      "start": 20.705,
      "end": 20.945,
      "confidence": 0.9665315,
      "punctuated_word": "with"
    },
    {
      "word": "his",
      "start": 20.945,
      "end": 21.185001,
      "confidence": 0.99968266,
      "punctuated_word": "his"
    },
    {
      "word": "lightning",
      "start": 21.185001,
      "end": 21.665,
      "confidence": 0.98810077,
      "punctuated_word": "lightning"
    },
    {
      "word": "fast",
      "start": 21.665,
      "end": 21.985,
      "confidence": 0.9970716,
      "punctuated_word": "fast"
    },
    {
      "word": "speed",
      "start": 21.985,
      "end": 22.485,
      "confidence": 0.9948925,
      "punctuated_word": "speed,"
    },
    {
      "word": "exceptional",
      "start": 22.785,
      "end": 23.285,
      "confidence": 0.9999081,
      "punctuated_word": "exceptional"
    },
    {
      "word": "ball",
      "start": 23.345001,
      "end": 23.585,
      "confidence": 0.99874264,
      "punctuated_word": "ball"
    },
    {
      "word": "control",
      "start": 23.585,
      "end": 24.085,
      "confidence": 0.99289274,
      "punctuated_word": "control,"
    },
    {
      "word": "and",
      "start": 24.145,
      "end": 24.385,
      "confidence": 0.9997441,
      "punctuated_word": "and"
    },
    {
      "word": "powerful",
      "start": 24.385,
      "end": 24.865,
      "confidence": 0.9992925,
      "punctuated_word": "powerful"
    },
    {
      "word": "shooting",
      "start": 24.865,
      "end": 25.105,
      "confidence": 0.9998857,
      "punctuated_word": "shooting"
    },
    {
      "word": "ability",
      "start": 25.105,
      "end": 25.59,
      "confidence": 0.97519505,
      "punctuated_word": "ability."
    },
    {
      "word": "ronaldo",
      "start": 25.83,
      "end": 26.31,
      "confidence": 0.9893601,
      "punctuated_word": "Ronaldo"
    },
    {
      "word": "has",
      "start": 26.31,
      "end": 26.47,
      "confidence": 0.9993723,
      "punctuated_word": "has"
    },
    {
      "word": "won",
      "start": 26.47,
      "end": 26.710001,
      "confidence": 0.9980356,
      "punctuated_word": "won"
    },
    {
      "word": "numerous",
      "start": 26.710001,
      "end": 27.210001,
      "confidence": 0.99990714,
      "punctuated_word": "numerous"
    },
    {
      "word": "awards",
      "start": 27.27,
      "end": 27.67,
      "confidence": 0.99792093,
      "punctuated_word": "awards"
    },
    {
      "word": "and",
      "start": 27.67,
      "end": 27.83,
      "confidence": 0.99826753,
      "punctuated_word": "and"
    },
    {
      "word": "broken",
      "start": 27.83,
      "end": 28.23,
      "confidence": 0.9993318,
      "punctuated_word": "broken"
    },
    {
      "word": "records",
      "start": 28.23,
      "end": 28.73,
      "confidence": 0.7847614,
      "punctuated_word": "records,"
    },
    {
      "word": "inspiring",
      "start": 29.19,
      "end": 29.69,
      "confidence": 0.9993068,
      "punctuated_word": "inspiring"
    },
    {
      "word": "millions",
      "start": 29.75,
      "end": 30.23,
      "confidence": 0.90093523,
      "punctuated_word": "millions"
    },
    {
      "word": "of",
      "start": 30.23,
      "end": 30.470001,
      "confidence": 0.99982613,
      "punctuated_word": "of"
    },
    {
      "word": "fans",
      "start": 30.470001,
      "end": 30.869999,
      "confidence": 0.9997298,
      "punctuated_word": "fans"
    },
    {
      "word": "around",
      "start": 30.869999,
      "end": 31.11,
      "confidence": 0.9996575,
      "punctuated_word": "around"
    },
    {
      "word": "the",
      "start": 31.11,
      "end": 31.27,
      "confidence": 0.999673,
      "punctuated_word": "the"
    },
    {
      "word": "world",
      "start": 31.27,
      "end": 31.59,
      "confidence": 0.9998299,
      "punctuated_word": "world"
    },
    {
      "word": "with",
      "start": 31.59,
      "end": 31.75,
      "confidence": 0.99836487,
      "punctuated_word": "with"
    },
    {
      "word": "his",
      "start": 31.75,
      "end": 32.07,
      "confidence": 0.99916565,
      "punctuated_word": "his"
    },
    {
      "word": "incredible",
      "start": 32.07,
      "end": 32.57,
      "confidence": 0.999892,
      "punctuated_word": "incredible"
    },
    {
      "word": "talent",
      "start": 32.63,
      "end": 33.03,
      "confidence": 0.99982256,
      "punctuated_word": "talent"
    },
    {
      "word": "and",
      "start": 33.03,
      "end": 33.27,
      "confidence": 0.99704236,
      "punctuated_word": "and"
    },
    {
      "word": "perseverance",
      "start": 33.27,
      "end": 33.77,
      "confidence": 0.9932788,
      "punctuated_word": "perseverance."
    },
    {
      "word": "but",
      "start": 34.79,
      "end": 35.03,
      "confidence": 0.99860305,
      "punctuated_word": "But"
    },
    {
      "word": "ronaldo's",
      "start": 35.03,
      "end": 35.53,
      "confidence": 0.9807712,
      "punctuated_word": "Ronaldo's"
    },
    {
      "word": "impact",
      "start": 35.67,
      "end": 36.07,
      "confidence": 0.916004,
      "punctuated_word": "impact"
    },
    {
      "word": "goes",
      "start": 36.07,
      "end": 36.39,
      "confidence": 0.9951107,
      "punctuated_word": "goes"
    },
    {
      "word": "beyond",
      "start": 36.39,
      "end": 36.79,
      "confidence": 0.99991906,
      "punctuated_word": "beyond"
    },
    {
      "word": "the",
      "start": 36.79,
      "end": 36.95,
      "confidence": 0.999703,
      "punctuated_word": "the"
    },
    {
      "word": "soccer",
      "start": 36.95,
      "end": 37.35,
      "confidence": 0.99962497,
      "punctuated_word": "soccer"
    },
    {
      "word": "field",
      "start": 37.35,
      "end": 37.75,
      "confidence": 0.9999069,
      "punctuated_word": "field"
    },
    {
      "word": "as",
      "start": 37.75,
      "end": 37.91,
      "confidence": 0.98550355,
      "punctuated_word": "as"
    },
    {
      "word": "he",
      "start": 37.91,
      "end": 38.07,
      "confidence": 0.9998185,
      "punctuated_word": "he"
    },
    {
      "word": "uses",
      "start": 38.07,
      "end": 38.47,
      "confidence": 0.9997675,
      "punctuated_word": "uses"
    },
    {
      "word": "his",
      "start": 38.47,
      "end": 38.71,
      "confidence": 0.99937457,
      "punctuated_word": "his"
    },
    {
      "word": "platform",
      "start": 38.71,
      "end": 39.21,
      "confidence": 0.9996512,
      "punctuated_word": "platform"
    },
    {
      "word": "to",
      "start": 39.27,
      "end": 39.510002,
      "confidence": 0.9997811,
      "punctuated_word": "to"
    },
    {
      "word": "make",
      "start": 39.510002,
      "end": 40.010002,
      "confidence": 0.999826,
      "punctuated_word": "make"
    },
    {
      "word": "a",
      "start": 40.176,
      "end": 40.336,
      "confidence": 0.9997404,
      "punctuated_word": "a"
    },
    {
      "word": "positive",
      "start": 40.336,
      "end": 40.736,
      "confidence": 0.999925,
      "punctuated_word": "positive"
    },
    {
      "word": "difference",
      "start": 40.736,
      "end": 41.135998,
      "confidence": 0.99987066,
      "punctuated_word": "difference"
    },
    {
      "word": "in",
      "start": 41.135998,
      "end": 41.216,
      "confidence": 0.9998894,
      "punctuated_word": "in"
    },
    {
      "word": "the",
      "start": 41.216,
      "end": 41.376,
      "confidence": 0.9999497,
      "punctuated_word": "the"
    },
    {
      "word": "world",
      "start": 41.376,
      "end": 41.856,
      "confidence": 0.9130064,
      "punctuated_word": "world,"
    },
    {
      "word": "supporting",
      "start": 41.856,
      "end": 42.336,
      "confidence": 0.9995091,
      "punctuated_word": "supporting"
    },
    {
      "word": "important",
      "start": 42.336,
      "end": 42.836,
      "confidence": 0.9998264,
      "punctuated_word": "important"
    },
    {
      "word": "causes",
      "start": 42.896,
      "end": 43.396,
      "confidence": 0.9273813,
      "punctuated_word": "causes,"
    },
    {
      "word": "and",
      "start": 43.455997,
      "end": 43.856,
      "confidence": 0.9991258,
      "punctuated_word": "and"
    },
    {
      "word": "inspiring",
      "start": 43.856,
      "end": 44.356,
      "confidence": 0.9993536,
      "punctuated_word": "inspiring"
    },
    {
      "word": "young",
      "start": 44.496,
      "end": 44.736,
      "confidence": 0.99989235,
      "punctuated_word": "young"
    },
    {
      "word": "people",
      "start": 44.736,
      "end": 45.135998,
      "confidence": 0.99992454,
      "punctuated_word": "people"
    },
    {
      "word": "to",
      "start": 45.135998,
      "end": 45.376,
      "confidence": 0.99961996,
      "punctuated_word": "to"
    },
    {
      "word": "chase",
      "start": 45.376,
      "end": 45.696,
      "confidence": 0.99955755,
      "punctuated_word": "chase"
    },
    {
      "word": "their",
      "start": 45.696,
      "end": 45.935997,
      "confidence": 0.9998486,
      "punctuated_word": "their"
    },
    {
      "word": "dreams",
      "start": 45.935997,
      "end": 46.336,
      "confidence": 0.99983954,
      "punctuated_word": "dreams"
    },
    {
      "word": "and",
      "start": 46.336,
      "end": 46.576,
      "confidence": 0.95442146,
      "punctuated_word": "and"
    },
    {
      "word": "never",
      "start": 46.576,
      "end": 46.896,
      "confidence": 0.9999652,
      "punctuated_word": "never"
    },
    {
      "word": "give",
      "start": 46.896,
      "end": 47.056,
      "confidence": 0.99992776,
      "punctuated_word": "give"
    },
    {
      "word": "up",
      "start": 47.056,
      "end": 47.295998,
      "confidence": 0.9999256,
      "punctuated_word": "up"
    },
    {
      "word": "on",
      "start": 47.295998,
      "end": 47.455997,
      "confidence": 0.99952865,
      "punctuated_word": "on"
    },
    {
      "word": "their",
      "start": 47.455997,
      "end": 47.696,
      "confidence": 0.99975866,
      "punctuated_word": "their"
    },
    {
      "word": "passions",
      "start": 47.696,
      "end": 48.196,
      "confidence": 0.99789596,
      "punctuated_word": "passions."
    }
  ],
  "lastModified": {
    "user": "keshavsingh2004"
  }
}